setup.py
MtkM/MtkM.py
MtkM/__init__.py
MtkM.egg-info/PKG-INFO
MtkM.egg-info/SOURCES.txt
MtkM.egg-info/dependency_links.txt
MtkM.egg-info/top_level.txt